argusvision/__init__.py
argusvision/models/__init__.py
argusvision/models/resnext.py
argusvision/models/utils.py
argusvision-1.1.0.dist-info/METADATA
argusvision-1.1.0.dist-info/WHEEL
argusvision-1.1.0.dist-info/top_level.txt
argusvision-1.1.0.dist-info/RECORD
