Metadata-Version: 2.1
Name: argusvision
Version: 1.1.0
Summary: Downloads pretrained Argus Vision models
Home-page: UNKNOWN
License: UNKNOWN
Platform: UNKNOWN
Requires-Dist: torch (>=1.2.0)
Requires-Dist: azure-storage-blob
Requires-Dist: azure-identity
Requires-Dist: tqdm
